aldryn_django/__init__.py
aldryn_django/cli.py
aldryn_django/context_processors.py
aldryn_django/i18n_urls.py
aldryn_django/middleware.py
aldryn_django/models.py
aldryn_django/startup.py
aldryn_django/storage.py
aldryn_django/urls_redirect.py
aldryn_django/utils.py
aldryn_django/management/__init__.py
aldryn_django/management/commands/__init__.py
aldryn_django/management/commands/aldryn_collectstatic.py
aldryn_django/management/commands/aldryn_optimize_static_images.py
aldryn_django/management/commands/aldryn_update_s3_media_headers.py
aldryn_django/monkeypatches/__init__.py
aldryn_django/monkeypatches/hide_secrets_in_debug_mode.py
tests/__init__.py
tests/settings.py
tests/test_migrations.py
aldryn_django-5.1.5.0.dist-info/LICENSE
aldryn_django-5.1.5.0.dist-info/METADATA
aldryn_django-5.1.5.0.dist-info/WHEEL
aldryn_django-5.1.5.0.dist-info/entry_points.txt
aldryn_django-5.1.5.0.dist-info/top_level.txt
aldryn_django-5.1.5.0.dist-info/RECORD
