Metadata-Version: 2.1
Name: aldryn-django
Version: 5.1.5.0
Summary: An opinionated Django setup bundled as an Aldryn Addon
Home-page: https://github.com/divio/aldryn-django
Author: Divio AG
Author-email: info@divio.ch
License: BSD-3-Clause
Classifier: Development Status :: 5 - Production/Stable
Classifier: Environment :: Web Environment
Classifier: Intended Audience :: Developers
Classifier: License :: OSI Approved :: BSD License
Classifier: Operating System :: OS Independent
Classifier: Framework :: Django
Classifier: Framework :: Django :: 5.1
Classifier: Programming Language :: Python
Classifier: Programming Language :: Python :: 3
Classifier: Programming Language :: Python :: 3.10
Classifier: Programming Language :: Python :: 3.11
Classifier: Programming Language :: Python :: 3.12
Classifier: Topic :: Internet :: WWW/HTTP
Classifier: Topic :: Internet :: WWW/HTTP :: Dynamic Content
Classifier: Topic :: Software Development
Classifier: Topic :: Software Development :: Libraries
License-File: LICENSE
Requires-Dist: aldryn-addons
Requires-Dist: Django ==5.1.5
Requires-Dist: dj-database-url
Requires-Dist: dj-email-url
Requires-Dist: dj-redis-url
Requires-Dist: django-cache-url
Requires-Dist: django-getenv
Requires-Dist: aldryn-client
Requires-Dist: furl
Requires-Dist: aiocontextvars
Requires-Dist: sentry-sdk
Requires-Dist: uwsgi
Requires-Dist: psycopg2
Requires-Dist: django-storage-url
Requires-Dist: django-storages[boto3]
Requires-Dist: django-storages[azure]
Requires-Dist: click
Requires-Dist: aldryn-sites >=0.5.6
Requires-Dist: easy-thumbnails >=2.2
